maturin_import_hook/__init__.py
maturin_import_hook/__main__.py
maturin_import_hook/_building.py
maturin_import_hook/_common.py
maturin_import_hook/_logging.py
maturin_import_hook/_resolve_project.py
maturin_import_hook/_site.py
maturin_import_hook/error.py
maturin_import_hook/project_importer.py
maturin_import_hook/py.typed
maturin_import_hook/rust_file_importer.py
maturin_import_hook/settings.py
maturin_import_hook-0.3.0.dist-info/METADATA
maturin_import_hook-0.3.0.dist-info/WHEEL
maturin_import_hook-0.3.0.dist-info/top_level.txt
maturin_import_hook-0.3.0.dist-info/RECORD
