Metadata-Version: 2.4
Name: maturin-import-hook
Version: 0.3.0
Summary: Import hook to load rust projects built with maturin
Author-email: Matthew Broadway <mattdbway@gmail.com>
Project-URL: Homepage, https://github.com/PyO3/maturin-import-hook
Project-URL: Documentation, https://maturin.rs
Project-URL: Repository, https://github.com/PyO3/maturin-import-hook.git
Project-URL: Issues, https://github.com/PyO3/maturin-import-hook/issues
Project-URL: Changelog, https://github.com/PyO3/maturin-import-hook/blob/main/Changelog.md
Classifier: Development Status :: 5 - Production/Stable
Classifier: Intended Audience :: Developers
Classifier: Topic :: Software Development :: Build Tools
Classifier: Programming Language :: Python :: 3
Classifier: Programming Language :: Rust
Classifier: License :: OSI Approved :: MIT License
Classifier: License :: OSI Approved :: Apache Software License
Requires-Python: >=3.9
Requires-Dist: filelock
Requires-Dist: tomli>=1.1.0; python_version < "3.11"
